{
  "id": "376",
  "name": "Metagross",
  "format_id": "showdown_gen5ou-1500",
  "usage_metrics": {
    "raw": 2692,
    "base_weight": 1435.2605622448461,
    "percent": 3.3495085230807513
  },
  "items": {
    "life-orb": 65.5587049889365,
    "choice-scarf": 17.094668365039837,
    "leftovers": 559.0486874764267,
    "custap-berry": 183.75942476829874,
    "air-balloon": 44.99792636492446,
    "shuca-berry": 277.4222203673142,
    "sitrus-berry": 2.6650664919303346,
    "choice-band": 53.60625500705963,
    "rocky-helmet": 121.061103168965,
    "lum-berry": 9.308529239750785,
    "wide-lens": 0.1122039737332674,
    "scope-lens": 3.4683944605262695e-10,
    "occa-berry": 93.41155873280232,
    "light-clay": 2.7245951023102677e-7,
    "expert-belt": 2.1982816757601964,
    "focus-sash": 2.11887165575173,
    "nothing": 0.7777677942149657,
    "muscle-band": 0.37250832839847825,
    "chesto-berry": 1.0535199072638748,
    "quick-claw": 0.00001695383757416291,
    "iron-ball": 0.5650942672186261,
    "salac-berry": 0.12815244441166856
  },
  "abilities": {
    "clear-body": 1434.885006516707,
    "light-metal": 0.3755557281391032
  },
  "moves": {
    "zen-headbutt": 370.8982022202217,
    "earthquake": 1036.9489383798425,
    "ice-punch": 624.7179064321641,
    "agility": 180.52982306450244,
    "trick": 17.962202459962498,
    "meteor-mash": 766.921486320437,
    "pursuit": 577.4020078541218,
    "explosion": 262.7973463148472,
    "bullet-punch": 578.8695546435982,
    "psychic": 10.108113011892073,
    "stealth-rock": 690.713778513001,
    "hidden-power-fire": 4.893112518287861,
    "refresh": 1.8899596849931894,
    "light-screen": 2.6118378681020515,
    "hammer-arm": 146.14524970188654,
    "hidden-power-grass": 0.0009196754920233197,
    "toxic": 1.0355607188158584,
    "iron-defense": 0.4728850076463108,
    "iron-head": 13.32210830597059,
    "hone-claws": 119.1054220594407,
    "thunder-punch": 81.12163639056148,
    "rain-dance": 0.0009412917122564313,
    "endure": 1.6854773696511662,
    "gravity": 0.09561195006059009,
    "rock-polish": 117.97337528518902,
    "rock-slide": 9.01066657830201,
    "protect": 20.04451503003595,
    "reflect": 4.869972592413951e-7,
    "magnet-rise": 4.001284644795247,
    "shadow-ball": 1.7334807235680532,
    "brick-break": 88.62355863699521,
    "icy-wind": 0.8536758067698298,
    "defense-curl": 0.3718771984604321,
    "hyper-beam": 0.37187719846069217,
    "sleep-talk": 1.130967669866913,
    "body-slam": 2.411171425955316,
    "hidden-power-electric": 0.3528502144960992,
    "rest": 1.0535213062105153,
    "signal-beam": 0.3718771984604321,
    "headbutt": 0.0000015973699300508848,
    "metal-claw": 0.15069990159199537,
    "hidden-power-ice": 1.1691491309933175,
    "double-edge": 0.2885463082954908,
    "gyro-ball": 0.4057400237716712,
    "dynamic-punch": 0.4733308555852723
  },
  "teras": {
    "nothing": 1435.2605622448461
  },
  "spreads": [
    {
      "nature": "Adamant",
      "usage": "32.0",
      "evs": {
        "hp": 252,
        "atk": 252,
        "def": 0,
        "spa": 0,
        "spd": 4,
        "spe": 0
      }
    },
    {
      "nature": "Adamant",
      "usage": "14.9",
      "evs": {
        "hp": 252,
        "atk": 96,
        "def": 0,
        "spa": 0,
        "spd": 160,
        "spe": 0
      }
    },
    {
      "nature": "Adamant",
      "usage": "11.5",
      "evs": {
        "hp": 0,
        "atk": 252,
        "def": 0,
        "spa": 0,
        "spd": 4,
        "spe": 252
      }
    },
    {
      "nature": "Adamant",
      "usage": "7.6",
      "evs": {
        "hp": 252,
        "atk": 252,
        "def": 4,
        "spa": 0,
        "spd": 0,
        "spe": 0
      }
    },
    {
      "nature": "Impish",
      "usage": "7.2",
      "evs": {
        "hp": 252,
        "atk": 0,
        "def": 252,
        "spa": 0,
        "spd": 0,
        "spe": 4
      }
    },
    {
      "nature": "Adamant",
      "usage": "6.6",
      "evs": {
        "hp": 252,
        "atk": 252,
        "def": 0,
        "spa": 0,
        "spd": 0,
        "spe": 4
      }
    },
    {
      "nature": "Jolly",
      "usage": "2.5",
      "evs": {
        "hp": 0,
        "atk": 252,
        "def": 0,
        "spa": 0,
        "spd": 4,
        "spe": 252
      }
    },
    {
      "nature": "Adamant",
      "usage": "1.8",
      "evs": {
        "hp": 204,
        "atk": 252,
        "def": 0,
        "spa": 0,
        "spd": 52,
        "spe": 0
      }
    },
    {
      "nature": "Adamant",
      "usage": "1.8",
      "evs": {
        "hp": 80,
        "atk": 252,
        "def": 104,
        "spa": 0,
        "spd": 72,
        "spe": 0
      }
    },
    {
      "nature": "Impish",
      "usage": "1.5",
      "evs": {
        "hp": 252,
        "atk": 0,
        "def": 252,
        "spa": 0,
        "spd": 4,
        "spe": 0
      }
    }
  ],
  "teammates": {
    "3": 1.998658387377349,
    "6": 8.02521898321164,
    "9": 32.45081313603928,
    "31": 0.5498870332988808,
    "34": 1.661992624487895,
    "36": 2.9802354039429235,
    "49": 1,
    "51": 0.17447882087819722,
    "52": 0.3528502144960992,
    "54": 0.3528502144960992,
    "57": 0.3718771984604321,
    "59": 5.328718844959929,
    "65": 163.86828131688992,
    "68": 19.0178156742429,
    "73": 20.004718294843435,
    "76": 2.9484354428453727,
    "80": 3.3544374472061778,
    "82": 0.000129157461421614,
    "93": 0.2885463082954908,
    "94": 118.64455946480116,
    "101": 0.0029361906645447022,
    "103": 0.009319251895553993,
    "105": 2.866107284670461,
    "106": 10.986510368431501,
    "110": 4.121727745524788,
    "112": 0.8368092296134515,
    "113": 12.326686938610763,
    "121": 368.98023527977915,
    "127": 1.1868041417088795,
    "128": 0.09437930028571151,
    "130": 247.1613274104322,
    "132": 0,
    "134": 11.185427720760938,
    "135": 20.68168973427232,
    "136": 0.6167387512589968,
    "141": 48.17098509291568,
    "142": 5.621138299601954,
    "143": 15.165151004721848,
    "145": 100.61686745959743,
    "148": 1.907544248143516,
    "149": 231.50855745483983,
    "151": 4.078486514431603,
    "160": 7.474096725140306,
    "168": 0.357263378291777,
    "169": 2.186515530338239,
    "171": 29.75222523855404,
    "178": 60.79242352389398,
    "181": 0.9927296263602796,
    "184": 6.762982015794262,
    "186": 394.34531675788173,
    "195": 0.3383217113601453,
    "196": 3.011002781986631,
    "197": 14.555228406948224,
    "199": 19.530510511110545,
    "205": 13.431532978645148,
    "208": 0.3864333664836279,
    "212": 317.99451279832516,
    "213": 0.17800983483844868,
    "214": 17.911960161310883,
    "217": 2.5437030692477283,
    "227": 138.4886491885979,
    "230": 1.2497238219886717,
    "232": 39.08918145819476,
    "233": 4.893827209557346,
    "237": 7.33596877818167,
    "242": 27.408001022915496,
    "243": 19.497182922861416,
    "244": 4.381644802243576,
    "245": 10.267246818824493,
    "248": 162.6194260729503,
    "251": 23.644146836329682,
    "254": 2.42882392846749,
    "260": 1.4200453281932406,
    "272": 7.498565874443386,
    "277": 0.9332876182134648,
    "279": 0.042198933191657795,
    "282": 2.858415061995373,
    "286": 322.0282787222088,
    "291": 0.00044429883667834735,
    "295": 0.00044429883667834735,
    "297": 6.085907673841259,
    "301": 0.11897761894933973,
    "302": 20.981844326427712,
    "303": 0.11897761894933973,
    "305": 2.8081145495318203,
    "306": 0.05560941059698393,
    "308": 0.0015498629573034717,
    "310": 1.0175112579642482,
    "319": 1.1963370440422954,
    "323": 0.9846315766678843,
    "324": 1.3685970600102524,
    "327": 2.832004287106596,
    "340": 0.042198933191657795,
    "342": 3.8318677984570986,
    "344": 0.8171979819902876,
    "346": 30.603068920713252,
    "348": 0.05560941059672386,
    "350": 4.422033235293476,
    "356": 1.1798981720843935,
    "359": 0.21789114448182068,
    "365": 1.407087465436615,
    "366": 0.908817201241275,
    "368": 0.11897761894933973,
    "373": 180.93664289884268,
    "377": 0.8055583743075492,
    "379": 1.141371306656152,
    "380": 20.08368740351433,
    "381": 193.53278378476364,
    "385": 38.462582471965355,
    "389": 4.579330944454725,
    "392": 25.35019269965142,
    "395": 0.13691940647448525,
    "398": 36.95921226706569,
    "407": 0.00023731637750079582,
    "409": 2.5883036667231565,
    "416": 0.00005965545766473124,
    "419": 0.00009369968527134231,
    "423": 22.6331636912805,
    "424": 0.17533221497556112,
    "426": 0.00001695383757416291,
    "429": 0.3389702417467736,
    "430": 34.70185858986582,
    "437": 3.109993688533464,
    "442": 3.16304845278479,
    "445": 223.1848186782948,
    "447": 1.3529581344151609e-9,
    "448": 19.686889145543212,
    "450": 22.177208709394886,
    "452": 2.6413487837347844,
    "454": 120.19369525098149,
    "460": 12.535265870273403,
    "461": 61.74114019201646,
    "462": 37.39503052739542,
    "463": 2.9484354428453727,
    "464": 3.933736319113334,
    "465": 0.966907847416546,
    "466": 7.326625376252431,
    "467": 2.5426912190021675,
    "468": 31.806410769526405,
    "469": 0.6160386721862138,
    "471": 0.2292629064066234,
    "472": 47.80013658452387,
    "473": 157.01486836722347,
    "474": 2.8320061393604226,
    "475": 0.0015498629573034717,
    "477": 13.274657969066002,
    "478": 34.79377194660284,
    "479": 1.2618368834536215,
    "482": 28.73544509925232,
    "485": 42.289775016133575,
    "486": 0.001178608089757227,
    "488": 7.218621632142946,
    "492": 0.10197392591041798,
    "494": 5.515769361907684,
    "497": 0.7818346850465736,
    "500": 0.3718771984604321,
    "503": 1.8684189497315402,
    "508": 0.5999055901847155,
    "510": 0.3718771984604321,
    "518": 0.009648556676620346,
    "521": 0.19668938340508357,
    "526": 5.818116272398453,
    "528": 0.0015498629573034717,
    "530": 83.08126896586339,
    "534": 101.81029938431344,
    "537": 11.3442396884714,
    "538": 2.7696297398009597,
    "542": 0.7108474402072057,
    "545": 1.3122326586701125,
    "547": 3.8517950918114034,
    "553": 1.9717711526685577,
    "555": 5.395267129941624,
    "558": 0.00001695383757416291,
    "560": 2.423709042521961,
    "561": 2.2670850812972114,
    "563": 12.516363296313504,
    "565": 0.3718771984604321,
    "567": 0.056550702308980294,
    "571": 11.563289080090236,
    "573": 0.04315207950525546,
    "579": 44.42326043028712,
    "586": 0.02833151734369105,
    "589": 0.36119397211453325,
    "591": 0.7917979955102248,
    "593": 27.345639802299168,
    "596": 2.869680829553078,
    "598": 42.02208774854147,
    "601": 0.036010428872703115,
    "604": 5.973943052294815,
    "606": 0.00012919220128232434,
    "609": 195.65551554894012,
    "612": 47.18099711789099,
    "617": 0.8536758067698298,
    "620": 149.18372438705603,
    "621": 8.370848537892543,
    "623": 4.342451078774742,
    "625": 0.6565409201947985,
    "628": 0.13691940647445638,
    "630": 0.4414515237747115,
    "635": 108.22185813660833,
    "637": 194.9766216202804,
    "639": 31.169392327464784,
    "640": 11.933575480661478,
    "641": 138.71258451140756,
    "646": 16.18377305120305,
    "647": 346.5267641529841,
    "648": 43.62233979911702,
    "10008": 3.560342271665548,
    "10009": 100.78476265830709,
    "10010": 0.0000013989466404740192,
    "10020": 143.29759567883866,
    "10021": 69.64905925871525,
    "10022": 97.67256196425654
  }
}