{
  "id": "635",
  "name": "Hydreigon",
  "format_id": "showdown_gen5ou-0",
  "usage_metrics": {
    "raw": 4764,
    "base_weight": 4764,
    "percent": 5.927584919746174
  },
  "items": {
    "choice-specs": 1544,
    "choice-scarf": 1454,
    "life-orb": 914,
    "leftovers": 488,
    "white-herb": 32,
    "rocky-helmet": 6,
    "expert-belt": 57,
    "haban-berry": 22,
    "focus-sash": 40,
    "choice-band": 11,
    "wise-glasses": 61,
    "sitrus-berry": 10,
    "black-glasses": 12,
    "nothing": 6,
    "petaya-berry": 4,
    "lum-berry": 33,
    "dragon-fang": 29,
    "scope-lens": 8,
    "persim-berry": 14,
    "chesto-berry": 1,
    "dread-plate": 5,
    "draco-plate": 2,
    "zoom-lens": 2,
    "metronome": 1,
    "wide-lens": 3,
    "salac-berry": 4,
    "chople-berry": 1
  },
  "abilities": {
    "levitate": 4764
  },
  "moves": {
    "draco-meteor": 3755,
    "flamethrower": 1896,
    "dark-pulse": 3742,
    "u-turn": 1478,
    "dragon-pulse": 1219,
    "focus-blast": 1006,
    "fire-blast": 2192,
    "surf": 617,
    "superpower": 193,
    "thunder-wave": 42,
    "roost": 558,
    "earth-power": 1105,
    "aqua-tail": 7,
    "flash-cannon": 74,
    "hidden-power-ice": 33,
    "tri-attack": 68,
    "taunt": 130,
    "heat-wave": 91,
    "dragon-tail": 78,
    "crunch": 60,
    "earthquake": 38,
    "outrage": 88,
    "tailwind": 13,
    "substitute": 168,
    "protect": 48,
    "acrobatics": 57,
    "body-slam": 5,
    "hidden-power-electric": 18,
    "hidden-power-grass": 13,
    "work-up": 40,
    "frustration": 8,
    "ice-fang": 25,
    "dragon-rush": 14,
    "assurance": 7,
    "focus-energy": 9,
    "hidden-power-fighting": 26,
    "rest": 2,
    "iron-tail": 3,
    "hidden-power-flying": 25,
    "fire-fang": 17,
    "charge-beam": 15,
    "hidden-power-psychic": 3,
    "fly": 1,
    "payback": 5,
    "toxic": 27,
    "hidden-power-ghost": 2,
    "torment": 3,
    "hidden-power-dragon": 2,
    "thunder-fang": 2,
    "facade": 9,
    "head-smash": 3,
    "sleep-talk": 1,
    "hidden-power-dark": 1,
    "dragon-rage": 1,
    "rain-dance": 3,
    "reflect": 3,
    "hyper-voice": 3,
    "hidden-power-rock": 2,
    "sunny-day": 1,
    "": 1
  },
  "teras": {
    "nothing": 4764
  },
  "spreads": [
    {
      "nature": "Timid",
      "usage": "35.3",
      "evs": {
        "hp": 0,
        "atk": 0,
        "def": 0,
        "spa": 252,
        "spd": 4,
        "spe": 252
      }
    },
    {
      "nature": "Modest",
      "usage": "12.6",
      "evs": {
        "hp": 0,
        "atk": 0,
        "def": 0,
        "spa": 252,
        "spd": 4,
        "spe": 252
      }
    },
    {
      "nature": "Timid",
      "usage": "10.6",
      "evs": {
        "hp": 4,
        "atk": 0,
        "def": 0,
        "spa": 252,
        "spd": 0,
        "spe": 252
      }
    },
    {
      "nature": "Modest",
      "usage": "6.5",
      "evs": {
        "hp": 20,
        "atk": 0,
        "def": 0,
        "spa": 252,
        "spd": 4,
        "spe": 232
      }
    },
    {
      "nature": "Modest",
      "usage": "3.8",
      "evs": {
        "hp": 4,
        "atk": 0,
        "def": 0,
        "spa": 252,
        "spd": 0,
        "spe": 252
      }
    },
    {
      "nature": "Hasty",
      "usage": "3.7",
      "evs": {
        "hp": 0,
        "atk": 4,
        "def": 0,
        "spa": 252,
        "spd": 0,
        "spe": 252
      }
    },
    {
      "nature": "Modest",
      "usage": "2.1",
      "evs": {
        "hp": 0,
        "atk": 0,
        "def": 0,
        "spa": 252,
        "spd": 0,
        "spe": 252
      }
    },
    {
      "nature": "Modest",
      "usage": "1.9",
      "evs": {
        "hp": 252,
        "atk": 0,
        "def": 0,
        "spa": 252,
        "spd": 4,
        "spe": 0
      }
    },
    {
      "nature": "Modest",
      "usage": "1.7",
      "evs": {
        "hp": 36,
        "atk": 0,
        "def": 0,
        "spa": 252,
        "spd": 0,
        "spe": 220
      }
    },
    {
      "nature": "Timid",
      "usage": "1.6",
      "evs": {
        "hp": 0,
        "atk": 0,
        "def": 4,
        "spa": 252,
        "spd": 0,
        "spe": 252
      }
    }
  ],
  "teammates": {
    "3": 80,
    "6": 30,
    "9": 38,
    "12": 6,
    "20": 5,
    "25": 8,
    "26": 8,
    "31": 12,
    "34": 81,
    "36": 40,
    "38": 267,
    "59": 37,
    "62": 16,
    "65": 566,
    "68": 23,
    "73": 149,
    "80": 10,
    "89": 2,
    "94": 286,
    "103": 2,
    "106": 4,
    "107": 126,
    "110": 20,
    "113": 211,
    "114": 5,
    "121": 577,
    "123": 1,
    "130": 259,
    "131": 37,
    "132": 7,
    "134": 42,
    "135": 159,
    "139": 11,
    "141": 9,
    "142": 8,
    "143": 7,
    "145": 190,
    "146": 3,
    "148": 4,
    "149": 268,
    "151": 3,
    "154": 6,
    "157": 8,
    "160": 17,
    "168": 13,
    "169": 37,
    "171": 2,
    "178": 37,
    "184": 17,
    "186": 144,
    "189": 1,
    "195": 31,
    "196": 168,
    "197": 101,
    "199": 16,
    "205": 580,
    "208": 2,
    "212": 633,
    "213": 10,
    "214": 40,
    "217": 55,
    "221": 72,
    "226": 7,
    "227": 425,
    "229": 7,
    "230": 233,
    "232": 105,
    "233": 38,
    "235": 6,
    "237": 144,
    "242": 123,
    "243": 15,
    "244": 3,
    "245": 6,
    "248": 1048,
    "251": 140,
    "254": 1,
    "256": 1,
    "260": 14,
    "272": 11,
    "277": 5,
    "279": 5,
    "282": 7,
    "286": 145,
    "289": 2,
    "291": 1,
    "297": 61,
    "302": 39,
    "304": 5,
    "306": 36,
    "308": 15,
    "310": 4,
    "319": 5,
    "321": 1,
    "324": 6,
    "330": 15,
    "332": 8,
    "334": 15,
    "335": 1,
    "342": 1,
    "344": 11,
    "350": 20,
    "351": 2,
    "356": 6,
    "357": 4,
    "359": 3,
    "373": 183,
    "376": 276,
    "380": 56,
    "381": 604,
    "385": 440,
    "392": 285,
    "395": 3,
    "398": 27,
    "405": 13,
    "407": 32,
    "414": 1,
    "416": 2,
    "423": 54,
    "424": 12,
    "426": 48,
    "429": 39,
    "430": 1,
    "432": 4,
    "437": 34,
    "442": 29,
    "445": 698,
    "447": 15,
    "448": 91,
    "450": 116,
    "451": 29,
    "452": 21,
    "454": 94,
    "460": 76,
    "461": 72,
    "462": 337,
    "463": 8,
    "464": 11,
    "465": 16,
    "466": 6,
    "468": 38,
    "469": 29,
    "472": 445,
    "473": 378,
    "474": 27,
    "475": 25,
    "477": 33,
    "478": 15,
    "479": 1,
    "480": 7,
    "481": 1,
    "482": 15,
    "485": 283,
    "488": 13,
    "492": 20,
    "494": 44,
    "497": 74,
    "500": 30,
    "503": 106,
    "505": 12,
    "508": 8,
    "510": 2,
    "518": 9,
    "521": 8,
    "523": 15,
    "526": 3,
    "530": 501,
    "533": 1,
    "534": 356,
    "537": 59,
    "538": 3,
    "539": 1,
    "545": 17,
    "547": 18,
    "549": 19,
    "550": 1,
    "553": 28,
    "555": 109,
    "556": 2,
    "558": 16,
    "560": 89,
    "561": 101,
    "563": 206,
    "565": 5,
    "567": 26,
    "569": 2,
    "571": 31,
    "576": 8,
    "579": 631,
    "581": 11,
    "586": 4,
    "589": 13,
    "591": 126,
    "593": 740,
    "594": 3,
    "596": 28,
    "598": 1003,
    "601": 1,
    "603": 2,
    "604": 94,
    "606": 2,
    "609": 260,
    "612": 181,
    "615": 4,
    "617": 12,
    "620": 201,
    "621": 21,
    "623": 25,
    "625": 114,
    "626": 38,
    "628": 12,
    "630": 7,
    "631": 1,
    "632": 1,
    "637": 408,
    "638": 3,
    "639": 138,
    "640": 6,
    "641": 53,
    "646": 23,
    "647": 327,
    "648": 28,
    "10008": 6,
    "10009": 739,
    "10010": 1,
    "10011": 1,
    "10012": 41,
    "10020": 68,
    "10021": 868,
    "10022": 155
  }
}