{
  "id": "230",
  "name": "Kingdra",
  "format_id": "showdown_gen4ou",
  "usage_metrics": {
    "raw": 10688,
    "base_weight": 102.65883353637172,
    "percent": 9.210934537557309
  },
  "items": {
    "chesto-berry": 10.0199356778193,
    "choice-band": 0.00004659192269229617,
    "leftovers": 24.239187762912728,
    "focus-sash": 0.010723282474951412,
    "choice-specs": 49.429899466167704,
    "lum-berry": 6.603382955138391,
    "life-orb": 7.011264401939447,
    "sea-incense": 0.01529298675696572,
    "scope-lens": 0.447223419785456,
    "mystic-water": 2.8490534563907155,
    "damp-rock": 0.027155853481977466,
    "sitrus-berry": 0.0000055195826977882945,
    "choice-scarf": 1.0990680840508014,
    "nothing": 1.0819642959347675e-9,
    "razor-claw": 0.0001172193621792883,
    "wide-lens": 0.04577824765111427,
    "haban-berry": 0.011515414030352278,
    "lansat-berry": 0.000004456636834015981,
    "dragon-fang": 0,
    "splash-plate": 0.8297604562771139,
    "expert-belt": 0.0017283706627975737,
    "white-herb": 5.887630327716664e-9,
    "power-herb": 2.121387166487132e-7,
    "wise-glasses": 0.0014140079918185666,
    "shell-bell": 0,
    "muscle-band": 0.01627568063657725,
    "never-melt-ice": 5.591326623921589e-9
  },
  "abilities": {
    "swift-swim": 98.71240467105477,
    "sniper": 3.9464288653169453
  },
  "moves": {
    "dragon-dance": 24.685161719323816,
    "rest": 12.269763232252668,
    "waterfall": 24.74693580405563,
    "outrage": 24.98062020097946,
    "iron-head": 0.07713047985154536,
    "draco-meteor": 54.79066454845791,
    "ice-beam": 23.00902740364917,
    "protect": 0.009150444790235301,
    "surf": 71.07113116815442,
    "signal-beam": 5.021910842053089,
    "rain-dance": 28.498173492219486,
    "hydro-pump": 56.33080703946097,
    "dragon-pulse": 65.89169316383378,
    "substitute": 11.066129951801967,
    "facade": 0,
    "hiddenpowerelectric": 7.176108062664722,
    "focus-energy": 0.43030801465196544,
    "flash-cannon": 0.05434726830925357,
    "hiddenpowergrass": 0.017075355620998878,
    "blizzard": 0.029985092186335993,
    "body-slam": 0.03848353755473588,
    "double-edge": 0.016480575345847126,
    "agility": 0.017604755958659568,
    "hiddenpowerfighting": 0.012103422007778974,
    "water-pulse": 0.021748945053239266,
    "hiddenpowerfire": 0.008854140349002726,
    "toxic": 0.3453110539613317,
    "octazooka": 1.0475231793094508e-11,
    "captivate": 1.0475231793094508e-11,
    "bounce": 0,
    "sleep-talk": 0.017984555840678096,
    "hiddenpowerground": 0.00006202030583030149,
    "muddy-water": 8.853128453112369e-7,
    "brine": 2.8499649751267953e-8,
    "icy-wind": 2.177300432726348e-7,
    "razor-wind": 2.121387166487132e-7,
    "disable": 0.0000017912218227555954,
    "return": 0.0005747198701309131,
    "whirlpool": 1.887379141862766e-15
  },
  "teras": {
    "nothing": 102.65883353637166
  },
  "spreads": [
    {
      "nature": "Modest",
      "usage": "30.2",
      "evs": {
        "hp": 0,
        "atk": 0,
        "def": 0,
        "spa": 252,
        "spd": 4,
        "spe": 252
      }
    },
    {
      "nature": "Modest",
      "usage": "15.9",
      "evs": {
        "hp": 184,
        "atk": 0,
        "def": 0,
        "spa": 252,
        "spd": 0,
        "spe": 72
      }
    },
    {
      "nature": "Modest",
      "usage": "9.7",
      "evs": {
        "hp": 0,
        "atk": 0,
        "def": 4,
        "spa": 252,
        "spd": 0,
        "spe": 252
      }
    },
    {
      "nature": "Modest",
      "usage": "6.9",
      "evs": {
        "hp": 4,
        "atk": 0,
        "def": 0,
        "spa": 252,
        "spd": 0,
        "spe": 252
      }
    },
    {
      "nature": "Adamant",
      "usage": "4.7",
      "evs": {
        "hp": 0,
        "atk": 252,
        "def": 0,
        "spa": 0,
        "spd": 4,
        "spe": 252
      }
    },
    {
      "nature": "Modest",
      "usage": "3.2",
      "evs": {
        "hp": 88,
        "atk": 0,
        "def": 4,
        "spa": 252,
        "spd": 0,
        "spe": 164
      }
    },
    {
      "nature": "Adamant",
      "usage": "2.9",
      "evs": {
        "hp": 184,
        "atk": 160,
        "def": 0,
        "spa": 0,
        "spd": 0,
        "spe": 164
      }
    },
    {
      "nature": "Modest",
      "usage": "2.7",
      "evs": {
        "hp": 28,
        "atk": 0,
        "def": 0,
        "spa": 252,
        "spd": 0,
        "spe": 228
      }
    },
    {
      "nature": "Adamant",
      "usage": "2.5",
      "evs": {
        "hp": 144,
        "atk": 152,
        "def": 0,
        "spa": 0,
        "spd": 40,
        "spe": 172
      }
    },
    {
      "nature": "Adamant",
      "usage": "2.5",
      "evs": {
        "hp": 136,
        "atk": 140,
        "def": 0,
        "spa": 0,
        "spd": 4,
        "spe": 228
      }
    }
  ],
  "teammates": {
    "3": 0.033708971207985106,
    "6": 0.0006691244195524138,
    "9": 0.10529134498207077,
    "12": 0.00008548590404822143,
    "15": 4.926810709404705e-7,
    "19": 0,
    "25": 0,
    "26": 0,
    "31": 0.00021984130376695443,
    "34": 4.5962122996456856e-12,
    "36": 0.06378294290503111,
    "47": 0,
    "53": 0.01602521348705105,
    "55": 4.807265696626928e-14,
    "57": 0,
    "59": 0.000023860535288910967,
    "62": 1.7179104805364886e-9,
    "65": 0.011036496242266935,
    "67": 0,
    "73": 0.016590843435987712,
    "80": 1.8781357252750652e-7,
    "82": 8.337921086631027,
    "87": 0,
    "91": 2.4054054859057317e-9,
    "94": 11.174298045983354,
    "101": 0.019285984736351625,
    "103": 7.462203077679419e-11,
    "105": 0.000369866495851634,
    "106": 6.015676757287203e-7,
    "107": 0.0005483885384504616,
    "110": 0.01919890104634231,
    "115": 0,
    "117": 0.0000017901538974518516,
    "119": 0,
    "121": 3.307478040448815,
    "127": 0.0191953450849196,
    "130": 28.859559411946357,
    "131": 0.0000017901538974518516,
    "132": 0.000005118015668603704,
    "134": 0.006956364627079437,
    "135": 1.401841775058159,
    "139": 0.902624510690688,
    "141": 8.607400664006244,
    "142": 2.4248301654597406,
    "143": 3.629275999172954e-7,
    "144": 0,
    "145": 3.3554647510889195,
    "146": 0.0005326861525607463,
    "148": 0.0000017901538974518516,
    "149": 12.882876343695107,
    "154": 0.00013074940652918476,
    "157": 0,
    "160": 0.28762890123744134,
    "168": 2.5942661352473806e-9,
    "169": 0.048315230516791374,
    "171": 0.0000062286513066167615,
    "181": 0.00046430678065406683,
    "184": 0.0003496700821830623,
    "185": 0.00046430678065406683,
    "186": 0.00003169692600285545,
    "189": 3.3806291099836017e-14,
    "195": 0.0026944072328394797,
    "196": 0,
    "197": 0.000047660691530726496,
    "200": 0,
    "205": 0.1433910085785785,
    "208": 0.018239572235241364,
    "211": 7.610920825224654,
    "212": 50.8563217727983,
    "213": 0,
    "214": 3.8869323230366724,
    "217": 0.028704928630345017,
    "224": 0.00009490585873289659,
    "226": 0,
    "227": 17.600037870288038,
    "229": 0.0005373135866235113,
    "232": 1.171477840091657,
    "235": 0.0008850825151119346,
    "237": 0.08745837526561151,
    "242": 0.4597015370578292,
    "243": 2.7378361523739922,
    "244": 1.3485135691437833e-7,
    "245": 2.24203909392024,
    "247": 0.0000017901538974518516,
    "248": 50.21748597350137,
    "251": 3.291018879471854,
    "254": 0.000201165968315542,
    "257": 0.00019097991697142325,
    "260": 5.443891336283737,
    "264": 8.881784197001252e-16,
    "272": 5.855349738865956,
    "275": 0,
    "277": 0.003130682399867135,
    "279": 0.00010319364660082986,
    "282": 0.000057468795940263107,
    "286": 4.720119692949679,
    "292": 0.011445441396498501,
    "297": 0.004517425467470582,
    "303": 0,
    "306": 0.00009698511953742939,
    "308": 3.7172325217937896e-9,
    "310": 0,
    "319": 0.0018833321845712625,
    "321": 0.04310239875665678,
    "327": 0,
    "330": 10.899275559420554,
    "334": 0.015899624264881562,
    "340": 0.7615727186801433,
    "342": 1.0754175328031579e-12,
    "344": 0.011678266158316575,
    "346": 0.000656730974283648,
    "348": 4.807265696626928e-14,
    "350": 0.025661781697362773,
    "359": 2.121387298603672e-7,
    "367": 0,
    "368": 0.01855947357283344,
    "369": 0,
    "372": 2.220446049250313e-16,
    "376": 23.07985040020504,
    "378": 0,
    "379": 3.710589779881701e-9,
    "380": 36.93651835666493,
    "385": 21.209454776849014,
    "389": 0.000941801710504564,
    "392": 16.759431974574486,
    "395": 16.83056179429646,
    "398": 0.00009110663544426023,
    "405": 0,
    "407": 0.16886968074234776,
    "409": 0.000004456636834015981,
    "411": 5.591326623921589e-9,
    "416": 0.0006564241525943704,
    "419": 4.197470014610847,
    "423": 0,
    "424": 0.018764892440111924,
    "426": 3.657626498343447e-7,
    "429": 0.11226810387062341,
    "430": 0.0463768066045277,
    "435": 0,
    "437": 16.92256402876288,
    "442": 0.0003206287983908429,
    "448": 10.996491895289417,
    "450": 0.28948409133506026,
    "452": 0.00006181048375891729,
    "454": 0.22751320427682703,
    "455": 4.377283535639265e-9,
    "460": 0.05318980761226144,
    "461": 2.5774325090678474,
    "462": 24.06164564697592,
    "463": 0,
    "464": 0.0022517153138636448,
    "466": 0.007370480892593179,
    "467": 0.000201165968315542,
    "468": 0.0694609066211142,
    "469": 0.009906634827853644,
    "470": 0.005099848583185462,
    "472": 7.947799215476962,
    "473": 3.119996455781533,
    "474": 0.5441570524144896,
    "475": 0.00490078180175052,
    "476": 0.00729889759688318,
    "477": 1.4069730935872826e-9,
    "480": 3.4219711959977177,
    "481": 0,
    "482": 14.996541292375378,
    "485": 13.984199185844258,
    "486": 0.000018242997352702073,
    "488": 0.2543694850463492,
    "489": 2.5942661352473806e-9,
    "492": 0.1942861396255134,
    "10008": 5.020397498802558,
    "10009": 32.040430982556096,
    "10010": 7.560618797697316e-14,
    "10012": 0.10288395571085862
  }
}