{
  "id": "26",
  "name": "Raichu",
  "format_id": "showdown_gen6doublesou-1630",
  "usage_metrics": {
    "raw": 131,
    "base_weight": 24.343524343782992,
    "percent": 4.969650986342944
  },
  "items": {
    "sitrus-berry": 0.007715885600612815,
    "leftovers": 0.03601605209738262,
    "life-orb": 0.14201457180164906,
    "assault-vest": 4.014141076498957,
    "air-balloon": 13.999997925388989,
    "focus-sash": 5.753841873741264,
    "nothing": 0,
    "magnet": 0.10114491950592347,
    "eject-button": 0,
    "normal-gem": 0.2886520391482158
  },
  "abilities": {
    "lightning-rod": 24.018856252537393,
    "static": 0.3246680912455984
  },
  "moves": {
    "nuzzle": 5.775810946936069,
    "thunder": 0.2886520391482158,
    "volt-switch": 18.156153573689597,
    "fake-out": 24.307508291685608,
    "discharge": 0.031905946430212384,
    "thunder-wave": 0.031905946430212384,
    "light-screen": 0.031905946430212384,
    "protect": 0.4078212125218097,
    "knock-off": 4.433605648318633,
    "nasty-plot": 0.14201457180164906,
    "helping-hand": 13.999997925388989,
    "encore": 19.385640418639273,
    "endeavor": 4.119952007182023,
    "electroweb": 0.46934302595637784,
    "agility": 0,
    "substitute": 0,
    "rest": 0.10114491950592347,
    "brick-break": 0.0041101056671702385,
    "extreme-speed": 0.0041101056671702385,
    "thunder-punch": 0.29276214481538604,
    "thunderbolt": 0.0041101056671702385,
    "volt-tackle": 5.38564249325028,
    "hidden-power-ice": 0,
    "electro-ball": 0,
    "grass-knot": 0
  },
  "teras": {
    "nothing": 24.343524343782992
  },
  "spreads": [
    {
      "nature": "Timid",
      "usage": "57.5",
      "evs": {
        "hp": 252,
        "atk": 0,
        "def": 0,
        "spa": 0,
        "spd": 4,
        "spe": 252
      }
    },
    {
      "nature": "Jolly",
      "usage": "22.2",
      "evs": {
        "hp": 0,
        "atk": 252,
        "def": 0,
        "spa": 0,
        "spd": 4,
        "spe": 252
      }
    },
    {
      "nature": "Timid",
      "usage": "16.4",
      "evs": {
        "hp": 116,
        "atk": 0,
        "def": 144,
        "spa": 0,
        "spd": 64,
        "spe": 184
      }
    },
    {
      "nature": "Naive",
      "usage": "1.5",
      "evs": {
        "hp": 4,
        "atk": 0,
        "def": 0,
        "spa": 252,
        "spd": 0,
        "spe": 252
      }
    },
    {
      "nature": "Hasty",
      "usage": "1.2",
      "evs": {
        "hp": 0,
        "atk": 252,
        "def": 0,
        "spa": 4,
        "spd": 0,
        "spe": 252
      }
    },
    {
      "nature": "Hasty",
      "usage": "0.6",
      "evs": {
        "hp": 0,
        "atk": 4,
        "def": 0,
        "spa": 252,
        "spd": 0,
        "spe": 252
      }
    },
    {
      "nature": "Modest",
      "usage": "0.4",
      "evs": {
        "hp": 252,
        "atk": 0,
        "def": 0,
        "spa": 4,
        "spd": 0,
        "spe": 252
      }
    },
    {
      "nature": "Timid",
      "usage": "0.1",
      "evs": {
        "hp": 64,
        "atk": 0,
        "def": 160,
        "spa": 180,
        "spd": 0,
        "spe": 104
      }
    },
    {
      "nature": "Jolly",
      "usage": "0.0",
      "evs": {
        "hp": 252,
        "atk": 0,
        "def": 128,
        "spa": 0,
        "spd": 128,
        "spe": 0
      }
    },
    {
      "nature": "Hardy",
      "usage": "0.0",
      "evs": {
        "hp": 112,
        "atk": 100,
        "def": 84,
        "spa": 72,
        "spd": 60,
        "spe": 80
      }
    }
  ],
  "teammates": {
    "3": 13.999997925388989,
    "51": 0.02188231924038503,
    "53": 0.008372477635915032,
    "57": 0,
    "59": 0.021998482170878186,
    "94": 0.02415095380371929,
    "121": 0.013626004534963154,
    "128": 0.00011616293049315773,
    "131": 0.002152471632841102,
    "142": 0.021998482170878186,
    "145": 0.2886520391482158,
    "149": 0,
    "184": 0,
    "186": 0.3427578005352278,
    "212": 0.2252607515589064,
    "230": 0,
    "235": 0.16093249653245217,
    "237": 3.3742278696456327,
    "245": 3.4983437016986154,
    "248": 3.273082950139709,
    "260": 0.10114491950592347,
    "272": 0.018917924730803115,
    "282": 0,
    "302": 2.3058157450591095,
    "350": 3.785315645146522,
    "376": 0,
    "378": 0.002152471632841102,
    "380": 13.999997925388989,
    "398": 0.007262927427519383,
    "423": 0.0000012740405301303603,
    "437": 0.0000012740405301303603,
    "445": 0.10114491950592347,
    "448": 0,
    "461": 0,
    "468": 3.273084224180239,
    "472": 0.007262927427519383,
    "485": 3.8042348439178553,
    "486": 0.002152471632841102,
    "488": 0.018917924730803115,
    "547": 0,
    "591": 0.2886520391482158,
    "596": 0,
    "598": 1.768151939235629,
    "609": 0.007262927427519383,
    "625": 0.006844607467541952,
    "635": 0,
    "639": 13.999997925388989,
    "641": 0.14201457180164906,
    "642": 0,
    "663": 0.2252607515589064,
    "681": 0,
    "700": 0.08790881041463705,
    "706": 0,
    "721": 0,
    "10009": 0,
    "10021": 18.246889205934455,
    "10022": 0.007262927427519383,
    "10033": 0,
    "10034": 0.002152471632841102,
    "10035": 14.087906735803628,
    "10036": 0.05410576138701201,
    "10038": 0,
    "10039": 3.8042335698773253,
    "10046": 0,
    "10050": 0.10114491950592347,
    "10051": 0,
    "10052": 0,
    "10058": 0,
    "10059": 0.007262927427519383,
    "10064": 0.2886520391482158,
    "10075": 0.2252607515589064,
    "10076": 3.273082950139709,
    "10088": 0.0000012740405301303603
  }
}