{"id":"egg-bomb","name":"egg-bomb","type":"normal","category":"physical","power":100,"accuracy":75,"pp":10,"priority":0,"flags":{"is_priority":false,"has_status":false,"has_buff":false,"has_debuff":false},"stats_affected":[],"flavorText":"This move can’t be used. It’s recommended that this move is forgotten. Once forgotten, this move can’t be remembered.","effectText":"Inflicts regular damage.","target":"selected-pokemon","tactics":{"ailment":"none","ailment_chance":0,"flinch_chance":0,"stat_chance":0,"effect_chance":null,"meta_category":"damage","stat_changes":[]},"is_sheer_force_boosted":false,"generation_introduced":1,"learners_by_gen":{"1":[{"pokemon_id":"102","method":"machine","level":0},{"pokemon_id":"103","method":"machine","level":0},{"pokemon_id":"113","method":"machine","level":0},{"pokemon_id":"151","method":"machine","level":0}],"2":[{"pokemon_id":"103","method":"level-up","level":31},{"pokemon_id":"113","method":"level-up","level":35},{"pokemon_id":"242","method":"level-up","level":28}],"3":[{"pokemon_id":"103","method":"level-up","level":31},{"pokemon_id":"113","method":"level-up","level":35},{"pokemon_id":"242","method":"level-up","level":28}],"4":[{"pokemon_id":"103","method":"level-up","level":27},{"pokemon_id":"113","method":"level-up","level":38},{"pokemon_id":"242","method":"level-up","level":38}],"5":[{"pokemon_id":"103","method":"level-up","level":27},{"pokemon_id":"113","method":"level-up","level":42},{"pokemon_id":"242","method":"level-up","level":42}],"6":[{"pokemon_id":"103","method":"level-up","level":27},{"pokemon_id":"113","method":"level-up","level":42},{"pokemon_id":"242","method":"level-up","level":42}],"7":[{"pokemon_id":"103","method":"level-up","level":1},{"pokemon_id":"103","method":"level-up","level":27},{"pokemon_id":"113","method":"level-up","level":35},{"pokemon_id":"113","method":"level-up","level":42},{"pokemon_id":"113","method":"level-up","level":44},{"pokemon_id":"242","method":"level-up","level":42},{"pokemon_id":"242","method":"level-up","level":44},{"pokemon_id":"10114","method":"level-up","level":1},{"pokemon_id":"10114","method":"level-up","level":27}]}}