{
  "format_id": "showdown_gen9bssregi",
  "total_teams_analyzed": 28141,
  "centralization_index": 33,
  "type_heatmap": {
    "psychic": 33584,
    "ghost": 49513,
    "dark": 59387,
    "ground": 57511,
    "fighting": 34725,
    "dragon": 54488,
    "ice": 24483,
    "electric": 17783,
    "fairy": 36948,
    "water": 36869,
    "fire": 20270,
    "flying": 45371,
    "rock": 19416,
    "poison": 25534,
    "steel": 27477,
    "normal": 18849,
    "bug": 1833,
    "grass": 4225
  },
  "gimmick_analysis": {
    "teras": {}
  },
  "top_pokemon": [
    {
      "id": "10194",
      "name": "Calyrex Shadow",
      "usage_rate": 38.47588927188089,
      "raw_count": 21655
    },
    {
      "id": "1003",
      "name": "Ting Lu",
      "usage_rate": 37.47201591983227,
      "raw_count": 21090
    },
    {
      "id": "1007",
      "name": "Koraidon",
      "usage_rate": 32.672968266941474,
      "raw_count": 18389
    },
    {
      "id": "1002",
      "name": "Chien Pao",
      "usage_rate": 31.734835293699586,
      "raw_count": 17861
    },
    {
      "id": "1008",
      "name": "Miraidon",
      "usage_rate": 29.528090686187415,
      "raw_count": 16619
    },
    {
      "id": "987",
      "name": "Flutter Mane",
      "usage_rate": 29.378842258626204,
      "raw_count": 16535
    },
    {
      "id": "10191",
      "name": "Urshifu Rapid Strike",
      "usage_rate": 23.646991933477842,
      "raw_count": 13309
    },
    {
      "id": "250",
      "name": "Ho Oh",
      "usage_rate": 23.09441739810241,
      "raw_count": 12998
    },
    {
      "id": "10021",
      "name": "Landorus Therian",
      "usage_rate": 22.16872179382396,
      "raw_count": 12477
    },
    {
      "id": "970",
      "name": "Glimmora",
      "usage_rate": 18.226075832415336,
      "raw_count": 10258
    },
    {
      "id": "977",
      "name": "Dondozo",
      "usage_rate": 15.992679719981522,
      "raw_count": 9001
    },
    {
      "id": "149",
      "name": "Dragonite",
      "usage_rate": 14.905298319178423,
      "raw_count": 8389
    },
    {
      "id": "10188",
      "name": "Zacian Crowned",
      "usage_rate": 14.439785366547031,
      "raw_count": 8127
    },
    {
      "id": "934",
      "name": "Garganacl",
      "usage_rate": 12.460466934366227,
      "raw_count": 7013
    },
    {
      "id": "382",
      "name": "Kyogre",
      "usage_rate": 11.763974272413916,
      "raw_count": 6621
    },
    {
      "id": "10272",
      "name": "Ursaluna Bloodmoon",
      "usage_rate": 11.6751359226751,
      "raw_count": 6571
    },
    {
      "id": "472",
      "name": "Gliscor",
      "usage_rate": 10.660601968657831,
      "raw_count": 6000
    },
    {
      "id": "861",
      "name": "Grimmsnarl",
      "usage_rate": 10.490032337159306,
      "raw_count": 5904
    },
    {
      "id": "990",
      "name": "Iron Treads",
      "usage_rate": 9.701147791478625,
      "raw_count": 5460
    },
    {
      "id": "10193",
      "name": "Calyrex Ice",
      "usage_rate": 9.594541771792048,
      "raw_count": 5400
    },
    {
      "id": "983",
      "name": "Kingambit",
      "usage_rate": 8.588891652748659,
      "raw_count": 4834
    },
    {
      "id": "778",
      "name": "Mimikyu Disguised",
      "usage_rate": 8.331260438506094,
      "raw_count": 4689
    },
    {
      "id": "980",
      "name": "Clodsire",
      "usage_rate": 7.878184854838137,
      "raw_count": 4434
    },
    {
      "id": "1018",
      "name": "Archaludon",
      "usage_rate": 7.16037098894851,
      "raw_count": 4030
    },
    {
      "id": "792",
      "name": "Lunala",
      "usage_rate": 6.423012686116343,
      "raw_count": 3615
    },
    {
      "id": "890",
      "name": "Eternatus",
      "usage_rate": 6.09253402508795,
      "raw_count": 3429
    },
    {
      "id": "1024",
      "name": "Terapagos",
      "usage_rate": 6.016133044312569,
      "raw_count": 3386
    },
    {
      "id": "132",
      "name": "Ditto",
      "usage_rate": 5.987704772396148,
      "raw_count": 3370
    },
    {
      "id": "594",
      "name": "Alomomola",
      "usage_rate": 5.831349276855833,
      "raw_count": 3282
    },
    {
      "id": "903",
      "name": "Sneasler",
      "usage_rate": 5.378273693187875,
      "raw_count": 3027
    },
    {
      "id": "1004",
      "name": "Chi Yu",
      "usage_rate": 5.300095945417718,
      "raw_count": 2983
    },
    {
      "id": "10113",
      "name": "Muk Alola",
      "usage_rate": 5.28943534344906,
      "raw_count": 2977
    },
    {
      "id": "249",
      "name": "Lugia",
      "usage_rate": 5.177499022778153,
      "raw_count": 2914
    },
    {
      "id": "235",
      "name": "Smeargle",
      "usage_rate": 5.044241498169931,
      "raw_count": 2839
    },
    {
      "id": "248",
      "name": "Tyranitar",
      "usage_rate": 3.811165203795174,
      "raw_count": 2145
    },
    {
      "id": "1000",
      "name": "Gholdengo",
      "usage_rate": 3.279911872357059,
      "raw_count": 1846
    },
    {
      "id": "212",
      "name": "Scizor",
      "usage_rate": 3.2568139014249673,
      "raw_count": 1833
    },
    {
      "id": "730",
      "name": "Primarina",
      "usage_rate": 3.0080665221562843,
      "raw_count": 1693
    },
    {
      "id": "727",
      "name": "Incineroar",
      "usage_rate": 2.830389822678654,
      "raw_count": 1593
    },
    {
      "id": "10273",
      "name": "Ogerpon Wellspring Mask",
      "usage_rate": 2.761095909882378,
      "raw_count": 1554
    },
    {
      "id": "10274",
      "name": "Ogerpon Hearthflame Mask",
      "usage_rate": 2.706016133044313,
      "raw_count": 1523
    },
    {
      "id": "901",
      "name": "Ursaluna",
      "usage_rate": 2.627838385274155,
      "raw_count": 1479
    },
    {
      "id": "748",
      "name": "Toxapex",
      "usage_rate": 2.503464695639814,
      "raw_count": 1409
    },
    {
      "id": "823",
      "name": "Corviknight",
      "usage_rate": 2.393305141963683,
      "raw_count": 1347
    },
    {
      "id": "384",
      "name": "Rayquaza",
      "usage_rate": 2.2138516754912763,
      "raw_count": 1246
    },
    {
      "id": "10022",
      "name": "Kyurem Black",
      "usage_rate": 2.171209267616645,
      "raw_count": 1222
    },
    {
      "id": "233",
      "name": "Porygon2",
      "usage_rate": 2.139227461710671,
      "raw_count": 1204
    },
    {
      "id": "911",
      "name": "Skeledirge",
      "usage_rate": 2.084147684872606,
      "raw_count": 1173
    },
    {
      "id": "1021",
      "name": "Raging Bolt",
      "usage_rate": 2.068156781919619,
      "raw_count": 1164
    },
    {
      "id": "812",
      "name": "Rillaboom",
      "usage_rate": 2.039728510003198,
      "raw_count": 1148
    }
  ],
  "top_cores": [
    {
      "core": [
        "1002",
        "1003",
        "10194"
      ],
      "usage_rate": 0.1007283699137419
    },
    {
      "core": [
        "1003",
        "10191",
        "10194"
      ],
      "usage_rate": 0.08713771343919066
    },
    {
      "core": [
        "1003",
        "1007",
        "10194"
      ],
      "usage_rate": 0.0853383576817612
    },
    {
      "core": [
        "1003",
        "10194",
        "987"
      ],
      "usage_rate": 0.07835165028683427
    },
    {
      "core": [
        "1002",
        "1003",
        "1007"
      ],
      "usage_rate": 0.07707259429746
    },
    {
      "core": [
        "1003",
        "10194",
        "250"
      ],
      "usage_rate": 0.07679447090227334
    },
    {
      "core": [
        "1002",
        "1007",
        "10194"
      ],
      "usage_rate": 0.07555979643866588
    },
    {
      "core": [
        "1003",
        "1007",
        "987"
      ],
      "usage_rate": 0.06989965790855991
    },
    {
      "core": [
        "1003",
        "1018",
        "10194"
      ],
      "usage_rate": 0.0694489224241208
    },
    {
      "core": [
        "1003",
        "10194",
        "970"
      ],
      "usage_rate": 0.06868349294231042
    }
  ],
  "rogue_picks": [],
  "top_cut": []
}